{
  "$schema": "https://example.com/dtc/flow-schema/v1",
  "flowId": "D0261",
  "flowVersion": "001",
  "flowName": "Rejection of Agent Appointment",
  "status": "Operational",
  "ownership": "MRA",
  "description": "Rejection of appointment and terms of renewal of contractual terms.",
  "routes": [
    {
      "from": "HHDA",
      "to": "Supplier",
      "version": "15.4"
    },
    {
      "from": "HHDC",
      "to": "AMVLP",
      "version": "15.4"
    },
    {
      "from": "HHDC",
      "to": "Supplier",
      "version": "15.4"
    },
    {
      "from": "MA",
      "to": "Supplier",
      "version": "15.4"
    },
    {
      "from": "MOP",
      "to": "AMVLP",
      "version": "15.4"
    },
    {
      "from": "MOP",
      "to": "Supplier",
      "version": "15.4"
    },
    {
      "from": "NHHDA",
      "to": "Supplier",
      "version": "15.4"
    },
    {
      "from": "NHHDC",
      "to": "Supplier",
      "version": "15.4"
    }
  ],
  "groups": {
    "761": {
      "name": "Rejection of Contract Details",
      "parent": null,
      "level": 1,
      "cardinality": {
        "min": 1,
        "max": null
      },
      "condition": "",
      "fields": [
        {
          "ref": "J0003",
          "name": "MPAN Core",
          "format": "NUM(13)",
          "required": true
        },
        {
          "ref": "J0048",
          "name": "Contract Reference",
          "format": "CHAR(10)",
          "required": true
        },
        {
          "ref": "J0049",
          "name": "Effective from Settlement Date {REGI}",
          "format": "DATE(0)",
          "required": true
        },
        {
          "ref": "J1016",
          "name": "Rejection of Agent Appointment Code",
          "format": "CHAR(1)",
          "required": true
        }
      ]
    }
  },
  "rules": [],
  "notes": "Agents are not required to check all conditions implied by the Rejection of Agent Appointment Codes.  The codes merely allow appointment rejection where the Agent(s) has made the check(s) and wishes to reject the appointment. Where an AMVLP (Asset Metering Virtual Lead Party) is involved, the MPAN Core must contain an AMSID (Asset Metering System Identifier) and not an MPAN."
}