{
  "$schema": "https://example.com/dtc/flow-schema/v1",
  "flowId": "D0385",
  "flowVersion": "001",
  "flowName": "Metering System Half Hourly Metered Data",
  "status": "Operational",
  "ownership": "BSC",
  "description": "Metering System Half Hourly metered data for  use by the SVAA",
  "routes": [
    {
      "from": "HHDA",
      "to": "SVAA",
      "version": "15.4"
    }
  ],
  "groups": {
    "19I": {
      "name": "Data File Additional Header",
      "parent": null,
      "level": 1,
      "cardinality": {
        "min": 1,
        "max": 1
      },
      "condition": "",
      "fields": [
        {
          "ref": "J0073",
          "name": "Settlement Date",
          "format": "DATE(0)",
          "required": true
        },
        {
          "ref": "J0146",
          "name": "Settlement Code",
          "format": "CHAR(2)",
          "required": true
        },
        {
          "ref": "J1086",
          "name": "Run Type Code",
          "format": "CHAR(2)",
          "required": true
        },
        {
          "ref": "J1087",
          "name": "Run Number",
          "format": "NUM(7)",
          "required": true
        },
        {
          "ref": "J1104",
          "name": "GSP Group",
          "format": "(0)",
          "required": true
        }
      ]
    },
    "20I": {
      "name": "Supplier",
      "parent": null,
      "level": 1,
      "cardinality": {
        "min": 1,
        "max": null
      },
      "condition": "",
      "fields": [
        {
          "ref": "J0084",
          "name": "Supplier Id",
          "format": "(0)",
          "required": true
        }
      ]
    },
    "04M": {
      "name": "MPAN Cores",
      "parent": "20I",
      "level": 2,
      "cardinality": {
        "min": 1,
        "max": null
      },
      "condition": "",
      "fields": [
        {
          "ref": "J0003",
          "name": "MPAN Core",
          "format": "NUM(13)",
          "required": true
        },
        {
          "ref": "J0189",
          "name": "Distributor Id",
          "format": "CHAR(4)",
          "required": true
        },
        {
          "ref": "J0147",
          "name": "Line Loss Factor Class Id",
          "format": "CHAR(3)",
          "required": true
        },
        {
          "ref": "J1628",
          "name": "BM Unit Id",
          "format": "CHAR(11)",
          "required": true
        }
      ]
    },
    "05M": {
      "name": "Settlement Period Metering System Metered Data",
      "parent": "04M",
      "level": 3,
      "cardinality": {
        "min": 0,
        "max": null,
        "raw": "46,48,50"
      },
      "condition": "",
      "fields": [
        {
          "ref": "J0074",
          "name": "Settlement Period Id",
          "format": "NUM(2)",
          "required": true
        },
        {
          "ref": "J1872",
          "name": "Period Metering System Metered Data",
          "format": "NUM(9)",
          "required": true
        },
        {
          "ref": "J0160",
          "name": "Consumption Component Class Id",
          "format": "NUM(2)",
          "required": true
        }
      ]
    }
  },
  "rules": [],
  "notes": "The HHDA must only send this data to the SVAA where the HHDA has accepted a D0354 (Metering System Reporting Notification) received from the SVAA by issuing a D0355. The HHDA must not sent this flow to Suppliers in response to a D0354 (they should send a D0357 instead)."
}